README.rst
rpio_client.py
setup.py
rpio_client.egg-info/PKG-INFO
rpio_client.egg-info/SOURCES.txt
rpio_client.egg-info/dependency_links.txt
rpio_client.egg-info/top_level.txt