Metadata-Version: 1.1
Name: rpio-client
Version: 1.0.2
Summary: Client library for rpio-server
Home-page: https://github.com/zzzsochi/rpio-server/tree/master/client
Author: Alexander Zelenyak aka ZZZ
Author-email: zzz.sochi@gmail.com
License: BSD
Keywords: gpio,rpi,raspberry,raspberrypi,go
Platform: UNKNOWN
Classifier: License :: OSI Approved :: BSD License
Classifier: Operating System :: POSIX
Classifier: Programming Language :: Python
Classifier: Programming Language :: Python :: 3.4
Classifier: Programming Language :: Python :: 3.5
Classifier: Topic :: Software Development :: Libraries :: Python Modules
Classifier: Topic :: System :: Networking
